<?xml version="1.0" encoding="utf-8"?>
<SoundBanksInfo Platform="Mac" BasePlatform="Mac" SchemaVersion="12" SoundbankVersion="135">
	<RootPaths>
		<ProjectRoot>/Users/ianrue/Library/Application Support/Wwise2019/Bottles/Wwise2019x64/dosdevices/z:/Volumes/Samsung SSD (Evo 860)/PROJECTS/WWISE/FTW/FTW GAME AUDIO/From-the-Wood-Audio/DV3_WwiseProject/</ProjectRoot>
		<SourceFilesRoot>/Users/ianrue/Library/Application Support/Wwise2019/Bottles/Wwise2019x64/dosdevices/z:/Volumes/Samsung SSD (Evo 860)/PROJECTS/WWISE/FTW/FTW GAME AUDIO/From-the-Wood-Audio/DV3_WwiseProject/.cache/Mac/</SourceFilesRoot>
		<SoundBanksRoot>/Users/ianrue/Library/Application Support/Wwise2019/Bottles/Wwise2019x64/dosdevices/z:/Volumes/Samsung SSD (Evo 860)/PROJECTS/WWISE/FTW/FTW GAME AUDIO/From-the-Wood-Audio/DV3_WwiseProject/GeneratedSoundBanks/Mac/</SoundBanksRoot>
		<ExternalSourcesInputFile></ExternalSourcesInputFile>
		<ExternalSourcesOutputRoot>/Users/ianrue/Library/Application Support/Wwise2019/Bottles/Wwise2019x64/dosdevices/z:/Volumes/Samsung SSD (Evo 860)/PROJECTS/WWISE/FTW/FTW GAME AUDIO/From-the-Wood-Audio/DV3_WwiseProject/GeneratedSoundBanks/Mac</ExternalSourcesOutputRoot>
	</RootPaths>
	<DialogueEvents/>
	<StreamedFiles/>
	<MediaFilesNotInAnyBank/>
	<SoundBanks>
		<SoundBank Id="1355168291" Language="SFX" Hash="333202418">
			<ObjectPath>Init</ObjectPath>
			<ShortName>Init</ShortName>
			<Path>Init.bnk</Path>
			<GameParameters>
				<GameParameter Id="1006694123" Name="MUSIC_VOLUME" ObjectPath="\Game Parameters\Default Work Unit\MUSIC_VOLUME"/>
				<GameParameter Id="1564184899" Name="SFX_VOLUME" ObjectPath="\Game Parameters\Default Work Unit\SFX_VOLUME"/>
			</GameParameters>
			<StateGroups>
				<StateGroup Id="3092587493" Name="Pause" ObjectPath="\States\Default Work Unit\Pause">
					<States>
						<State Id="748895195" Name="None" ObjectPath="\States\Default Work Unit\Pause\None"/>
						<State Id="1651971902" Name="On" ObjectPath="\States\Default Work Unit\Pause\On"/>
						<State Id="930712164" Name="Off" ObjectPath="\States\Default Work Unit\Pause\Off"/>
					</States>
				</StateGroup>
			</StateGroups>
		</SoundBank>
		<SoundBank Id="3104675574" Language="SFX" Hash="3545593759">
			<ObjectPath>\SoundBanks\Default Work Unit\MySoundBank</ObjectPath>
			<ShortName>MySoundBank</ShortName>
			<Path>MySoundBank.bnk</Path>
			<GameParameters>
				<GameParameter Id="1006694123" Name="MUSIC_VOLUME" ObjectPath="\Game Parameters\Default Work Unit\MUSIC_VOLUME"/>
				<GameParameter Id="1564184899" Name="SFX_VOLUME" ObjectPath="\Game Parameters\Default Work Unit\SFX_VOLUME"/>
			</GameParameters>
			<StateGroups>
				<StateGroup Id="3092587493" Name="Pause" ObjectPath="\States\Default Work Unit\Pause">
					<States>
						<State Id="748895195" Name="None" ObjectPath="\States\Default Work Unit\Pause\None"/>
						<State Id="1651971902" Name="On" ObjectPath="\States\Default Work Unit\Pause\On"/>
						<State Id="930712164" Name="Off" ObjectPath="\States\Default Work Unit\Pause\Off"/>
					</States>
				</StateGroup>
			</StateGroups>
		</SoundBank>
	</SoundBanks>
</SoundBanksInfo>
